cyclops/__init__.py
cyclops/data/__init__.py
cyclops/data/aggregate.py
cyclops/data/clean.py
cyclops/data/constants.py
cyclops/data/df/__init__.py
cyclops/data/df/feature.py
cyclops/data/df/handle_types.py
cyclops/data/df/normalize.py
cyclops/data/df/split.py
cyclops/data/df/vectorized.py
cyclops/data/diagnoses.py
cyclops/data/features/__init__.py
cyclops/data/features/medical_image.py
cyclops/data/impute.py
cyclops/data/loader.py
cyclops/data/packaged_loading_scripts/__init__.py
cyclops/data/packaged_loading_scripts/medical_imagefolder/__init__.py
cyclops/data/packaged_loading_scripts/medical_imagefolder/medical_imagefolder.py
cyclops/data/preprocess.py
cyclops/data/slicer.py
cyclops/data/string_ops.py
cyclops/data/transforms.py
cyclops/data/utils.py
cyclops/evaluate/__init__.py
cyclops/evaluate/evaluator.py
cyclops/evaluate/fairness/__init__.py
cyclops/evaluate/fairness/config.py
cyclops/evaluate/fairness/evaluator.py
cyclops/evaluate/metrics/__init__.py
cyclops/evaluate/metrics/accuracy.py
cyclops/evaluate/metrics/auroc.py
cyclops/evaluate/metrics/average_precision.py
cyclops/evaluate/metrics/experimental/__init__.py
cyclops/evaluate/metrics/experimental/_stat_scores.py
cyclops/evaluate/metrics/experimental/accuracy.py
cyclops/evaluate/metrics/experimental/auroc.py
cyclops/evaluate/metrics/experimental/average_precision.py
cyclops/evaluate/metrics/experimental/confusion_matrix.py
cyclops/evaluate/metrics/experimental/distributed_backends/__init__.py
cyclops/evaluate/metrics/experimental/distributed_backends/base.py
cyclops/evaluate/metrics/experimental/distributed_backends/mpi4py.py
cyclops/evaluate/metrics/experimental/distributed_backends/non_distributed.py
cyclops/evaluate/metrics/experimental/distributed_backends/torch_distributed.py
cyclops/evaluate/metrics/experimental/f_score.py
cyclops/evaluate/metrics/experimental/functional/__init__.py
cyclops/evaluate/metrics/experimental/functional/_stat_scores.py
pycyclops-0.2.12.dist-info/LICENSE.md
pycyclops-0.2.12.dist-info/METADATA
pycyclops-0.2.12.dist-info/WHEEL
pycyclops-0.2.12.dist-info/RECORD
