Metadata-Version: 2.3
Name: pycyclops
Version: 0.2.12
Summary: Framework for healthcare ML implementation
License: Apache-2.0
Author: Vector AI Engineering
Author-email: cyclops@vectorinstitute.ai
Requires-Python: >=3.9,<3.12
Classifier: License :: OSI Approved :: Apache Software License
Classifier: Programming Language :: Python :: 3
Classifier: Programming Language :: Python :: 3.9
Classifier: Programming Language :: Python :: 3.10
Classifier: Programming Language :: Python :: 3.11
Provides-Extra: alibi
Provides-Extra: alibi-detect
Provides-Extra: all
Provides-Extra: monai
Provides-Extra: torch
Provides-Extra: torchvision
Provides-Extra: torchxrayvision
Provides-Extra: xgboost
Requires-Dist: Jinja2 (>=3.1.3,<4.0.0)
Requires-Dist: alibi-detect[torch] (>=0.12.0,<0.13.0) ; extra == "alibi-detect" or extra == "all"
Requires-Dist: alibi[shap] (>=0.9.4,<0.10.0) ; extra == "alibi" or extra == "all"
Requires-Dist: array-api-compat (==1.6)
Requires-Dist: datasets (>=2.15.0,<3.0.0)
Requires-Dist: hydra-core (>=1.2.0,<2.0.0)
Requires-Dist: kaleido (==0.2.1)
Requires-Dist: llvmlite (>=0.40.0,<0.41.0) ; extra == "alibi" or extra == "alibi-detect" or extra == "all"
Requires-Dist: matplotlib (>=3.8.3,<4.0.0)
Requires-Dist: monai[itk] (>=1.3.0,<2.0.0) ; extra == "monai" or extra == "all"
Requires-Dist: numpy (>=1.24.0,<2.0.0)
Requires-Dist: pandas[performance] (>=2.1,<3.0)
Requires-Dist: pillow (>=10.0.0,<11.0.0)
Requires-Dist: plotly (>=5.7.0,<6.0.0)
Requires-Dist: psutil (>=5.9.4,<6.0.0)
Requires-Dist: pyarrow (>=17.0.0,<18.0.0)
Requires-Dist: pybtex (>=0.24.0,<0.25.0)
Requires-Dist: pydantic (>=1.10.11,<2.0.0)
Requires-Dist: scikit-learn (>=1.3.0,<2.0.0)
Requires-Dist: scipy (>=1.11.0,<2.0.0)
Requires-Dist: scour (>=0.38.2,<0.39.0)
Requires-Dist: spdx-tools (>=0.8.1,<0.9.0)
Requires-Dist: torch (>=1.11.0,<2.0.0) ; extra == "torch" or extra == "torchxrayvision" or extra == "monai" or extra == "alibi-detect" or extra == "all"
Requires-Dist: torchvision (>=0.14.0,<0.15.0) ; extra == "torchvision" or extra == "all"
Requires-Dist: torchxrayvision (>=1.2.0,<2.0.0) ; extra == "torchxrayvision" or extra == "all"
Requires-Dist: xgboost (>=1.5.2,<2.0.0) ; extra == "xgboost" or extra == "all"
Project-URL: Documentation, https://vectorinstitute.github.io/cyclops/
Project-URL: Repository, https://github.com/VectorInstitute/cyclops
